topsisfolder/__init__.py
topsisfolder/topsisModule.py
Topsis_Uday_102053008-1.0.12.dist-info/LICENSE.txt
Topsis_Uday_102053008-1.0.12.dist-info/METADATA
Topsis_Uday_102053008-1.0.12.dist-info/WHEEL
Topsis_Uday_102053008-1.0.12.dist-info/entry_points.txt
Topsis_Uday_102053008-1.0.12.dist-info/top_level.txt
Topsis_Uday_102053008-1.0.12.dist-info/RECORD
